pythonz-0.2.1.dist-info/METADATA
pythonz-0.2.1.dist-info/WHEEL
pythonz/__init__.py
pythonz/enum.py
pythonz/pipe.py
pythonz/symbol.py
pythonz-0.2.1.dist-info/RECORD
