Metadata-Version: 2.1
Name: pythonz
Version: 0.2.1
Summary: Python but it's Z
Author-Email: Yuichiro Smith <yu-ichiro@s3i7h.com>
License: MIT
Requires-Python: >=3.8
Requires-Dist: pythonz_pipe>=0.1.1
Requires-Dist: pythonz_symbol>=0.1.0
Requires-Dist: pythonz_enum>=0.2.1
